MANIFEST.in
README
setup.py
oldowan/__init__.py
oldowan.fasta.egg-info/PKG-INFO
oldowan.fasta.egg-info/SOURCES.txt
oldowan.fasta.egg-info/dependency_links.txt
oldowan.fasta.egg-info/namespace_packages.txt
oldowan.fasta.egg-info/not-zip-safe
oldowan.fasta.egg-info/top_level.txt
oldowan/fasta/VERSION
oldowan/fasta/__init__.py
oldowan/fasta/fasta.py