Metadata-Version: 1.0
Name: oldowan.fasta
Version: 1.0.4
Summary: Read and write FASTA format.
